<?xml version="1.0" encoding="UTF-8" ?>
<!-- Generated by Oracle SOA Modeler version 1.0 at [4/6/15 5:04 PM]. -->
<composite name="LogProcessor"
           revision="1.4"
           label="2015-04-06_17-04-25_556"
           mode="active"
           state="on"
           xmlns="http://xmlns.oracle.com/sca/1.0"
           xmlns:xs="http://www.w3.org/2001/XMLSchema"
           xmlns:wsp="http://schemas.xmlsoap.org/ws/2004/09/policy"
           xmlns:orawsp="http://schemas.oracle.com/ws/2006/01/policy"
           xmlns:ui="http://xmlns.oracle.com/soa/designer/">
  <import namespace="http://oracle.com/sca/soapservice/MediatorExamples/LogProcessor/LogWebservice"
          location="LogWebservice.wsdl" importType="wsdl"/>
  <import namespace="http://xmlns.oracle.com/pcbpel/adapter/file/MediatorExamples/LogProcessor/ExampleFileAdapter"
          location="ExampleFileAdapter.wsdl" importType="wsdl"/>
  <import namespace="http://xmlns.oracle.com/pcbpel/adapter/db/MediatorExamples/LogProcessor/ExampleDatabaseAdapter"
          location="ExampleDatabaseAdapter.wsdl" importType="wsdl"/>
  <service name="LogWebservice" ui:wsdlLocation="LogWebservice.wsdl">
    <interface.wsdl interface="http://oracle.com/sca/soapservice/MediatorExamples/LogProcessor/LogWebservice#wsdl.interface(execute_ptt)"/>
    <binding.ws port="http://oracle.com/sca/soapservice/MediatorExamples/LogProcessor/LogWebservice#wsdl.endpoint(LogWebservice/execute_pt)">
      <property name="weblogic.wsee.wsat.transaction.flowOption"
                type="xs:string" many="false">NEVER</property>
    </binding.ws>
  </service>
  <component name="Mediator1">
    <implementation.mediator src="Mediator1.mplan"/>
  </component>
  <reference name="ExampleFileAdapter"
             ui:wsdlLocation="ExampleFileAdapter.wsdl">
    <interface.wsdl interface="http://xmlns.oracle.com/pcbpel/adapter/file/MediatorExamples/LogProcessor/ExampleFileAdapter#wsdl.interface(Write_ptt)"/>
    <binding.jca config="ExampleFileAdapter_file.jca"/>
  </reference>
  <reference name="ExampleDatabaseAdapter"
             ui:wsdlLocation="ExampleDatabaseAdapter.wsdl">
    <interface.wsdl interface="http://xmlns.oracle.com/pcbpel/adapter/db/MediatorExamples/LogProcessor/ExampleDatabaseAdapter#wsdl.interface(ExampleDatabaseAdapter_ptt)"/>
    <binding.jca config="ExampleDatabaseAdapter_db.jca"/>
    <property name="jca.retry.count" type="xs:int" many="false" override="may">4</property>
    <property name="jca.retry.interval" type="xs:int" many="false"
              override="may">1</property>
    <property name="jca.retry.backoff" type="xs:int" many="false"
              override="may">2</property>
    <property name="jca.retry.maxInterval" type="xs:string" many="false"
              override="may">120</property>
  </reference>
  <wire>
    <source.uri>LogWebservice</source.uri>
    <target.uri>Mediator1/Mediator1</target.uri>
  </wire>
  <wire>
    <source.uri>Mediator1/ExampleFileAdapter</source.uri>
    <target.uri>ExampleFileAdapter</target.uri>
  </wire>
  <wire>
    <source.uri>Mediator1/ExampleDatabaseAdapter</source.uri>
    <target.uri>ExampleDatabaseAdapter</target.uri>
  </wire>
</composite>
